delaynet/__init__.py
delaynet/_version.py
delaynet/connectivity.py
delaynet/decorators.py
delaynet/detrending.py
delaynet/evaluation.py
delaynet/network_reconstruction.py
delaynet/connectivities/__init__.py
delaynet/connectivities/continuous_ordinal_patterns.py
delaynet/connectivities/granger.py
delaynet/connectivities/gravity.py
delaynet/connectivities/linear_correlation.py
delaynet/connectivities/mutual_information.py
delaynet/connectivities/rank_correlation.py
delaynet/connectivities/transfer_entropy.py
delaynet/detrending_methods/__init__.py
delaynet/detrending_methods/delta.py
delaynet/detrending_methods/identity.py
delaynet/detrending_methods/second_difference.py
delaynet/detrending_methods/z_score.py
delaynet/network_analysis/__init__.py
delaynet/network_analysis/_normalisation.py
delaynet/network_analysis/metrics.py
delaynet/network_analysis/pruning.py
delaynet/preparation/__init__.py
delaynet/preparation/data_generator.py
delaynet/utils/__init__.py
delaynet/utils/bind_args.py
delaynet/utils/dict_lookup.py
delaynet/utils/lag_steps.py
delaynet/utils/logging.py
delaynet-0.3.2.dist-info/licenses/LICENSE
tests/__init__.py
tests/conftest.py
tests/test_connectivity.py
tests/test_connectivity_decorator_errors.py
tests/test_detrend.py
tests/test_evaluation.py
tests/test_general.py
tests/test_network_reconstruction.py
tests/connectivities/__init__.py
tests/connectivities/test_all_connectivities.py
tests/connectivities/test_connectivity_decorator.py
tests/connectivities/test_continuous_ordinal_patterns.py
tests/connectivities/test_granger.py
tests/connectivities/test_gravity.py
tests/connectivities/test_linear_correlation.py
tests/connectivities/test_mutual_information.py
tests/connectivities/test_rank_correlation.py
tests/connectivities/test_transfer_entropy.py
tests/detrending_methods/__init__.py
tests/detrending_methods/test_all_detrends.py
tests/detrending_methods/test_delta.py
tests/detrending_methods/test_detrending_decorator.py
tests/detrending_methods/test_second_difference.py
delaynet-0.3.2.dist-info/METADATA
delaynet-0.3.2.dist-info/WHEEL
delaynet-0.3.2.dist-info/top_level.txt
delaynet-0.3.2.dist-info/RECORD
