Metadata-Version: 2.4
Name: delaynet
Version: 0.3.2
Summary: Delay Propagation in Transportation Networks
Author: Carlson Büth, Massimiliano Zanin
Maintainer-email: Carlson Büth <code@cbueth.de>
License: BSD-3-Clause
Project-URL: Documentation, https://delaynet.readthedocs.io/
Project-URL: Repository, https://github.com/cbueth/delaynet
Project-URL: Issues, https://github.com/cbueth/delaynet/issues
Project-URL: Changelog, https://delaynet.readthedocs.io/en/latest/changelog/
Keywords: Delay Propagation,Transportation Networks,Information Flow,Information Theory
Classifier: Development Status :: 4 - Beta
Classifier: Intended Audience :: Science/Research
Classifier: License :: OSI Approved :: BSD License
Classifier: Topic :: Scientific/Engineering :: Physics
Classifier: Topic :: Scientific/Engineering :: Mathematics
Classifier: Topic :: Scientific/Engineering :: Information Analysis
Classifier: License :: OSI Approved :: BSD License
Classifier: Programming Language :: Python :: 3
Classifier: Programming Language :: Python :: 3.11
Classifier: Programming Language :: Python :: 3.12
Classifier: Programming Language :: Python :: 3.13
Classifier: Operating System :: OS Independent
Classifier: Natural Language :: English
Requires-Python: >=3.11
License-File: LICENSE
Requires-Dist: numpy
Requires-Dist: scipy
Requires-Dist: statsmodels
Requires-Dist: scikit-learn
Requires-Dist: numba
Requires-Dist: infomeasure>=0.5.0
Requires-Dist: igraph
Requires-Dist: synthatdelays>=1.0.2
Provides-Extra: lint
Requires-Dist: pre-commit; extra == "lint"
Requires-Dist: ruff; extra == "lint"
Provides-Extra: test
Requires-Dist: pytest; extra == "test"
Requires-Dist: pytest-cov; extra == "test"
Requires-Dist: coverage; extra == "test"
Provides-Extra: doc
Requires-Dist: sphinx; extra == "doc"
Requires-Dist: myst-nb; extra == "doc"
Requires-Dist: sphinx-design; extra == "doc"
Requires-Dist: sphinx-book-theme; extra == "doc"
Requires-Dist: sphinxcontrib-bibtex; extra == "doc"
Requires-Dist: matplotlib; extra == "doc"
Provides-Extra: all
Requires-Dist: delaynet[doc,lint,test]; extra == "all"
Dynamic: license-file
